.gitignore
.travis.yml
LICENSE.txt
README.md
bitbucket-pipelines.yml
development.sh
hem_systemd.service
requirements.txt
setup.cfg
setup.py
test_requires.txt
.github/workflows/codeql-analysis.yml
.github/workflows/pythonapp.yml
.vscode/launch.json
.vscode/settings.json
hemApp/__init__.py
hemApp/cli-thread.py
hemApp/cli.py
hemApp/development.sh
hemApp/hem.code-workspace
hemApp.egg-info/PKG-INFO
hemApp.egg-info/SOURCES.txt
hemApp.egg-info/dependency_links.txt
hemApp.egg-info/entry_points.txt
hemApp.egg-info/requires.txt
hemApp.egg-info/top_level.txt
hemApp/drivers/__init__.py
hemApp/drivers/discovery_consul.py
hemApp/drivers/discovery_dns.py
hemApp/drivers/discovery_file.py
hemApp/drivers/metrics_console.py
hemApp/drivers/metrics_graphite.py
hemApp/drivers/metrics_kafka.py
hemApp/drivers/metrics_prometheus.py
tests/hosts.yaml
tests/hosts_key.yaml
tests/hosts_keyed_objects.yaml
tests/test_cli.py
tests/test_cli.yaml
tests/test_driver_discovery_consul.py
tests/test_driver_discovery_dns.py
tests/test_driver_discovery_file.py
tests/test_driver_metrics_console.py
tests/test_driver_metrics_graphite.py
tests/test_driver_metrics_kafka.py
tests/test_driver_metrics_prometheus.py
tests/test_hem.py
tests/test_nosettings.yaml