Metadata-Version: 2.1
Name: hemApp
Version: 11
Summary: HTTP Endpoint Monitor - keeping the loose ends tied up
Home-page: https://rickymoorhouse.uk/blog/2018/introducing-hem/
Author: Ricky Moorhouse
Author-email: hem@rickymoorhouse.uk
License: MIT
Keywords: monitor,http
Platform: UNKNOWN
Classifier: Development Status :: 3 - Alpha
Classifier: Topic :: Utilities
Classifier: License :: OSI Approved :: MIT License
